{"name":"roblox-ts-game","className":"DataModel","filePaths":["default.project.json"],"children":[{"name":"ReplicatedStorage","className":"ReplicatedStorage","children":[{"name":"TS","className":"Folder","children":[{"name":"core","className":"Folder","children":[{"name":"GunSettings","className":"ModuleScript","filePaths":["out\\shared\\core\\GunSettings.luau"]}]},{"name":"messaging","className":"ModuleScript","filePaths":["out\\shared\\messaging.luau"]},{"name":"state","className":"Folder","children":[{"name":"atoms","className":"ModuleScript","filePaths":["out\\shared\\state\\atoms\\init.luau"],"children":[{"name":"GunStates","className":"ModuleScript","filePaths":["out\\shared\\state\\atoms\\GunStates.luau"]},{"name":"PlayerStates","className":"ModuleScript","filePaths":["out\\shared\\state\\atoms\\PlayerStates.luau"]}]}]}]},{"name":"rbxts_include","className":"Folder","children":[{"name":"Promise","className":"ModuleScript","filePaths":["include\\Promise.lua"]},{"name":"RuntimeLib","className":"ModuleScript","filePaths":["include\\RuntimeLib.lua"]},{"name":"node_modules","className":"Folder","children":[{"name":"@rbxts","className":"Folder","children":[{"name":"charm","className":"ModuleScript","filePaths":["node_modules\\@rbxts\\charm\\init.luau"],"children":[{"name":"src","className":"ModuleScript","filePaths":["node_modules\\@rbxts\\charm\\src\\init.luau"],"children":[{"name":"atom","className":"ModuleScript","filePaths":["node_modules\\@rbxts\\charm\\src\\atom.luau"]},{"name":"computed","className":"ModuleScript","filePaths":["node_modules\\@rbxts\\charm\\src\\computed.luau"]},{"name":"effect","className":"ModuleScript","filePaths":["node_modules\\@rbxts\\charm\\src\\effect.luau"]},{"name":"mapped","className":"ModuleScript","filePaths":["node_modules\\@rbxts\\charm\\src\\mapped.luau"]},{"name":"observe","className":"ModuleScript","filePaths":["node_modules\\@rbxts\\charm\\src\\observe.luau"]},{"name":"store","className":"ModuleScript","filePaths":["node_modules\\@rbxts\\charm\\src\\store.luau"]},{"name":"subscribe","className":"ModuleScript","filePaths":["node_modules\\@rbxts\\charm\\src\\subscribe.luau"]},{"name":"types","className":"ModuleScript","filePaths":["node_modules\\@rbxts\\charm\\src\\types.luau"]}]},{"name":"wally","className":"ModuleScript","filePaths":["node_modules\\@rbxts\\charm\\wally.toml"]}]},{"name":"charm-sync","className":"ModuleScript","filePaths":["node_modules\\@rbxts\\charm-sync\\init.luau"],"children":[{"name":"src","className":"ModuleScript","filePaths":["node_modules\\@rbxts\\charm-sync\\src\\init.luau"],"children":[{"name":"client","className":"ModuleScript","filePaths":["node_modules\\@rbxts\\charm-sync\\src\\client.luau"]},{"name":"flatten","className":"ModuleScript","filePaths":["node_modules\\@rbxts\\charm-sync\\src\\flatten.luau"]},{"name":"interval","className":"ModuleScript","filePaths":["node_modules\\@rbxts\\charm-sync\\src\\interval.luau"]},{"name":"patch","className":"ModuleScript","filePaths":["node_modules\\@rbxts\\charm-sync\\src\\patch.luau"]},{"name":"server","className":"ModuleScript","filePaths":["node_modules\\@rbxts\\charm-sync\\src\\server.luau"]},{"name":"types","className":"ModuleScript","filePaths":["node_modules\\@rbxts\\charm-sync\\src\\types.luau"]},{"name":"validate","className":"ModuleScript","filePaths":["node_modules\\@rbxts\\charm-sync\\src\\validate.luau"]}]},{"name":"wally","className":"ModuleScript","filePaths":["node_modules\\@rbxts\\charm-sync\\wally.toml"]}]},{"name":"destroyable","className":"Folder","children":[{"name":"out","className":"ModuleScript","filePaths":["node_modules\\@rbxts\\destroyable\\out\\init.luau"]}]},{"name":"flamework-meta-utils","className":"Folder","children":[{"name":"out","className":"ModuleScript","filePaths":["node_modules\\@rbxts\\flamework-meta-utils\\out\\init.luau"],"children":[{"name":"macros","className":"ModuleScript","filePaths":["node_modules\\@rbxts\\flamework-meta-utils\\out\\macros.luau"]}]}]},{"name":"maid","className":"Folder","children":[{"name":"Maid","className":"ModuleScript","filePaths":["node_modules\\@rbxts\\maid\\Maid.lua"]}]},{"name":"object-utils","className":"ModuleScript","filePaths":["node_modules\\@rbxts\\object-utils\\init.lua"]},{"name":"pretty-react-hooks","className":"Folder","children":[{"name":"out","className":"ModuleScript","filePaths":["node_modules\\@rbxts\\pretty-react-hooks\\out\\init.luau"],"children":[{"name":"init.spec","className":"ModuleScript","filePaths":["node_modules\\@rbxts\\pretty-react-hooks\\out\\init.spec.luau"]},{"name":"use-async","className":"ModuleScript","filePaths":["node_modules\\@rbxts\\pretty-react-hooks\\out\\use-async\\init.luau"],"children":[{"name":"use-async","className":"ModuleScript","filePaths":["node_modules\\@rbxts\\pretty-react-hooks\\out\\use-async\\use-async.luau"]},{"name":"use-async.spec","className":"ModuleScript","filePaths":["node_modules\\@rbxts\\pretty-react-hooks\\out\\use-async\\use-async.spec.luau"]}]},{"name":"use-async-callback","className":"ModuleScript","filePaths":["node_modules\\@rbxts\\pretty-react-hooks\\out\\use-async-callback\\init.luau"],"children":[{"name":"use-async-callback","className":"ModuleScript","filePaths":["node_modules\\@rbxts\\pretty-react-hooks\\out\\use-async-callback\\use-async-callback.luau"]},{"name":"use-async-callback.spec","className":"ModuleScript","filePaths":["node_modules\\@rbxts\\pretty-react-hooks\\out\\use-async-callback\\use-async-callback.spec.luau"]}]},{"name":"use-async-effect","className":"ModuleScript","filePaths":["node_modules\\@rbxts\\pretty-react-hooks\\out\\use-async-effect\\init.luau"],"children":[{"name":"use-async-effect","className":"ModuleScript","filePaths":["node_modules\\@rbxts\\pretty-react-hooks\\out\\use-async-effect\\use-async-effect.luau"]},{"name":"use-async-effect.spec","className":"ModuleScript","filePaths":["node_modules\\@rbxts\\pretty-react-hooks\\out\\use-async-effect\\use-async-effect.spec.luau"]}]},{"name":"use-binding-listener","className":"ModuleScript","filePaths":["node_modules\\@rbxts\\pretty-react-hooks\\out\\use-binding-listener\\init.luau"],"children":[{"name":"use-binding-listener","className":"ModuleScript","filePaths":["node_modules\\@rbxts\\pretty-react-hooks\\out\\use-binding-listener\\use-binding-listener.luau"]},{"name":"use-binding-listener.spec","className":"ModuleScript","filePaths":["node_modules\\@rbxts\\pretty-react-hooks\\out\\use-binding-listener\\use-binding-listener.spec.luau"]}]},{"name":"use-binding-state","className":"ModuleScript","filePaths":["node_modules\\@rbxts\\pretty-react-hooks\\out\\use-binding-state\\init.luau"],"children":[{"name":"use-binding-state","className":"ModuleScript","filePaths":["node_modules\\@rbxts\\pretty-react-hooks\\out\\use-binding-state\\use-binding-state.luau"]},{"name":"use-binding-state.spec","className":"ModuleScript","filePaths":["node_modules\\@rbxts\\pretty-react-hooks\\out\\use-binding-state\\use-binding-state.spec.luau"]}]},{"name":"use-camera","className":"ModuleScript","filePaths":["node_modules\\@rbxts\\pretty-react-hooks\\out\\use-camera\\init.luau"],"children":[{"name":"use-camera","className":"ModuleScript","filePaths":["node_modules\\@rbxts\\pretty-react-hooks\\out\\use-camera\\use-camera.luau"]},{"name":"use-camera.spec","className":"ModuleScript","filePaths":["node_modules\\@rbxts\\pretty-react-hooks\\out\\use-camera\\use-camera.spec.luau"]}]},{"name":"use-composed-ref","className":"ModuleScript","filePaths":["node_modules\\@rbxts\\pretty-react-hooks\\out\\use-composed-ref\\init.luau"],"children":[{"name":"use-composed-ref","className":"ModuleScript","filePaths":["node_modules\\@rbxts\\pretty-react-hooks\\out\\use-composed-ref\\use-composed-ref.luau"]},{"name":"use-composed-ref.spec","className":"ModuleScript","filePaths":["node_modules\\@rbxts\\pretty-react-hooks\\out\\use-composed-ref\\use-composed-ref.spec.luau"]}]},{"name":"use-debounce-callback","className":"ModuleScript","filePaths":["node_modules\\@rbxts\\pretty-react-hooks\\out\\use-debounce-callback\\init.luau"],"children":[{"name":"use-debounce-callback","className":"ModuleScript","filePaths":["node_modules\\@rbxts\\pretty-react-hooks\\out\\use-debounce-callback\\use-debounce-callback.luau"]},{"name":"use-debounce-callback.spec","className":"ModuleScript","filePaths":["node_modules\\@rbxts\\pretty-react-hooks\\out\\use-debounce-callback\\use-debounce-callback.spec.luau"]}]},{"name":"use-debounce-effect","className":"ModuleScript","filePaths":["node_modules\\@rbxts\\pretty-react-hooks\\out\\use-debounce-effect\\init.luau"],"children":[{"name":"use-debounce-effect","className":"ModuleScript","filePaths":["node_modules\\@rbxts\\pretty-react-hooks\\out\\use-debounce-effect\\use-debounce-effect.luau"]},{"name":"use-debounce-effect.spec","className":"ModuleScript","filePaths":["node_modules\\@rbxts\\pretty-react-hooks\\out\\use-debounce-effect\\use-debounce-effect.spec.luau"]}]},{"name":"use-debounce-state","className":"ModuleScript","filePaths":["node_modules\\@rbxts\\pretty-react-hooks\\out\\use-debounce-state\\init.luau"],"children":[{"name":"use-debounce-state","className":"ModuleScript","filePaths":["node_modules\\@rbxts\\pretty-react-hooks\\out\\use-debounce-state\\use-debounce-state.luau"]},{"name":"use-debounce-state.spec","className":"ModuleScript","filePaths":["node_modules\\@rbxts\\pretty-react-hooks\\out\\use-debounce-state\\use-debounce-state.spec.luau"]}]},{"name":"use-defer-callback","className":"ModuleScript","filePaths":["node_modules\\@rbxts\\pretty-react-hooks\\out\\use-defer-callback\\init.luau"],"children":[{"name":"use-defer-callback","className":"ModuleScript","filePaths":["node_modules\\@rbxts\\pretty-react-hooks\\out\\use-defer-callback\\use-defer-callback.luau"]},{"name":"use-defer-callback.spec","className":"ModuleScript","filePaths":["node_modules\\@rbxts\\pretty-react-hooks\\out\\use-defer-callback\\use-defer-callback.spec.luau"]}]},{"name":"use-defer-effect","className":"ModuleScript","filePaths":["node_modules\\@rbxts\\pretty-react-hooks\\out\\use-defer-effect\\init.luau"],"children":[{"name":"use-defer-effect","className":"ModuleScript","filePaths":["node_modules\\@rbxts\\pretty-react-hooks\\out\\use-defer-effect\\use-defer-effect.luau"]},{"name":"use-defer-effect.spec","className":"ModuleScript","filePaths":["node_modules\\@rbxts\\pretty-react-hooks\\out\\use-defer-effect\\use-defer-effect.spec.luau"]}]},{"name":"use-defer-state","className":"ModuleScript","filePaths":["node_modules\\@rbxts\\pretty-react-hooks\\out\\use-defer-state\\init.luau"],"children":[{"name":"use-defer-state","className":"ModuleScript","filePaths":["node_modules\\@rbxts\\pretty-react-hooks\\out\\use-defer-state\\use-defer-state.luau"]},{"name":"use-defer-state.spec","className":"ModuleScript","filePaths":["node_modules\\@rbxts\\pretty-react-hooks\\out\\use-defer-state\\use-defer-state.spec.luau"]}]},{"name":"use-event-listener","className":"ModuleScript","filePaths":["node_modules\\@rbxts\\pretty-react-hooks\\out\\use-event-listener\\init.luau"],"children":[{"name":"use-event-listener","className":"ModuleScript","filePaths":["node_modules\\@rbxts\\pretty-react-hooks\\out\\use-event-listener\\use-event-listener.luau"]},{"name":"use-event-listener.spec","className":"ModuleScript","filePaths":["node_modules\\@rbxts\\pretty-react-hooks\\out\\use-event-listener\\use-event-listener.spec.luau"]}]},{"name":"use-interval","className":"ModuleScript","filePaths":["node_modules\\@rbxts\\pretty-react-hooks\\out\\use-interval\\init.luau"],"children":[{"name":"use-interval","className":"ModuleScript","filePaths":["node_modules\\@rbxts\\pretty-react-hooks\\out\\use-interval\\use-interval.luau"]},{"name":"use-interval.spec","className":"ModuleScript","filePaths":["node_modules\\@rbxts\\pretty-react-hooks\\out\\use-interval\\use-interval.spec.luau"]}]},{"name":"use-key-press","className":"ModuleScript","filePaths":["node_modules\\@rbxts\\pretty-react-hooks\\out\\use-key-press\\init.luau"],"children":[{"name":"use-key-press","className":"ModuleScript","filePaths":["node_modules\\@rbxts\\pretty-react-hooks\\out\\use-key-press\\use-key-press.luau"]},{"name":"use-key-press.spec","className":"ModuleScript","filePaths":["node_modules\\@rbxts\\pretty-react-hooks\\out\\use-key-press\\use-key-press.spec.luau"]}]},{"name":"use-latest","className":"ModuleScript","filePaths":["node_modules\\@rbxts\\pretty-react-hooks\\out\\use-latest\\init.luau"],"children":[{"name":"use-latest","className":"ModuleScript","filePaths":["node_modules\\@rbxts\\pretty-react-hooks\\out\\use-latest\\use-latest.luau"]},{"name":"use-latest.spec","className":"ModuleScript","filePaths":["node_modules\\@rbxts\\pretty-react-hooks\\out\\use-latest\\use-latest.spec.luau"]}]},{"name":"use-latest-callback","className":"ModuleScript","filePaths":["node_modules\\@rbxts\\pretty-react-hooks\\out\\use-latest-callback\\init.luau"],"children":[{"name":"use-latest-callback","className":"ModuleScript","filePaths":["node_modules\\@rbxts\\pretty-react-hooks\\out\\use-latest-callback\\use-latest-callback.luau"]},{"name":"use-latest-callback.spec","className":"ModuleScript","filePaths":["node_modules\\@rbxts\\pretty-react-hooks\\out\\use-latest-callback\\use-latest-callback.spec.luau"]}]},{"name":"use-lifetime","className":"ModuleScript","filePaths":["node_modules\\@rbxts\\pretty-react-hooks\\out\\use-lifetime\\init.luau"],"children":[{"name":"use-lifetime","className":"ModuleScript","filePaths":["node_modules\\@rbxts\\pretty-react-hooks\\out\\use-lifetime\\use-lifetime.luau"]},{"name":"use-lifetime.spec","className":"ModuleScript","filePaths":["node_modules\\@rbxts\\pretty-react-hooks\\out\\use-lifetime\\use-lifetime.spec.luau"]}]},{"name":"use-motion","className":"ModuleScript","filePaths":["node_modules\\@rbxts\\pretty-react-hooks\\out\\use-motion\\init.luau"],"children":[{"name":"use-motion","className":"ModuleScript","filePaths":["node_modules\\@rbxts\\pretty-react-hooks\\out\\use-motion\\use-motion.luau"]},{"name":"use-motion.spec","className":"ModuleScript","filePaths":["node_modules\\@rbxts\\pretty-react-hooks\\out\\use-motion\\use-motion.spec.luau"]}]},{"name":"use-mount-effect","className":"ModuleScript","filePaths":["node_modules\\@rbxts\\pretty-react-hooks\\out\\use-mount-effect\\init.luau"],"children":[{"name":"use-mount-effect","className":"ModuleScript","filePaths":["node_modules\\@rbxts\\pretty-react-hooks\\out\\use-mount-effect\\use-mount-effect.luau"]},{"name":"use-mount-effect.spec","className":"ModuleScript","filePaths":["node_modules\\@rbxts\\pretty-react-hooks\\out\\use-mount-effect\\use-mount-effect.spec.luau"]}]},{"name":"use-mouse","className":"ModuleScript","filePaths":["node_modules\\@rbxts\\pretty-react-hooks\\out\\use-mouse\\init.luau"],"children":[{"name":"use-mouse","className":"ModuleScript","filePaths":["node_modules\\@rbxts\\pretty-react-hooks\\out\\use-mouse\\use-mouse.luau"]},{"name":"use-mouse.spec","className":"ModuleScript","filePaths":["node_modules\\@rbxts\\pretty-react-hooks\\out\\use-mouse\\use-mouse.spec.luau"]}]},{"name":"use-previous","className":"ModuleScript","filePaths":["node_modules\\@rbxts\\pretty-react-hooks\\out\\use-previous\\init.luau"],"children":[{"name":"use-previous","className":"ModuleScript","filePaths":["node_modules\\@rbxts\\pretty-react-hooks\\out\\use-previous\\use-previous.luau"]},{"name":"use-previous.spec","className":"ModuleScript","filePaths":["node_modules\\@rbxts\\pretty-react-hooks\\out\\use-previous\\use-previous.spec.luau"]}]},{"name":"use-spring","className":"ModuleScript","filePaths":["node_modules\\@rbxts\\pretty-react-hooks\\out\\use-spring\\init.luau"],"children":[{"name":"use-spring","className":"ModuleScript","filePaths":["node_modules\\@rbxts\\pretty-react-hooks\\out\\use-spring\\use-spring.luau"]},{"name":"use-spring.spec","className":"ModuleScript","filePaths":["node_modules\\@rbxts\\pretty-react-hooks\\out\\use-spring\\use-spring.spec.luau"]}]},{"name":"use-tagged","className":"ModuleScript","filePaths":["node_modules\\@rbxts\\pretty-react-hooks\\out\\use-tagged\\init.luau"],"children":[{"name":"use-tagged","className":"ModuleScript","filePaths":["node_modules\\@rbxts\\pretty-react-hooks\\out\\use-tagged\\use-tagged.luau"]},{"name":"use-tagged.spec","className":"ModuleScript","filePaths":["node_modules\\@rbxts\\pretty-react-hooks\\out\\use-tagged\\use-tagged.spec.luau"]}]},{"name":"use-throttle-callback","className":"ModuleScript","filePaths":["node_modules\\@rbxts\\pretty-react-hooks\\out\\use-throttle-callback\\init.luau"],"children":[{"name":"use-throttle-callback","className":"ModuleScript","filePaths":["node_modules\\@rbxts\\pretty-react-hooks\\out\\use-throttle-callback\\use-throttle-callback.luau"]},{"name":"use-throttle-callback.spec","className":"ModuleScript","filePaths":["node_modules\\@rbxts\\pretty-react-hooks\\out\\use-throttle-callback\\use-throttle-callback.spec.luau"]}]},{"name":"use-throttle-effect","className":"ModuleScript","filePaths":["node_modules\\@rbxts\\pretty-react-hooks\\out\\use-throttle-effect\\init.luau"],"children":[{"name":"use-throttle-effect","className":"ModuleScript","filePaths":["node_modules\\@rbxts\\pretty-react-hooks\\out\\use-throttle-effect\\use-throttle-effect.luau"]},{"name":"use-throttle-effect.spec","className":"ModuleScript","filePaths":["node_modules\\@rbxts\\pretty-react-hooks\\out\\use-throttle-effect\\use-throttle-effect.spec.luau"]}]},{"name":"use-throttle-state","className":"ModuleScript","filePaths":["node_modules\\@rbxts\\pretty-react-hooks\\out\\use-throttle-state\\init.luau"],"children":[{"name":"use-throttle-state","className":"ModuleScript","filePaths":["node_modules\\@rbxts\\pretty-react-hooks\\out\\use-throttle-state\\use-throttle-state.luau"]},{"name":"use-throttle-state.spec","className":"ModuleScript","filePaths":["node_modules\\@rbxts\\pretty-react-hooks\\out\\use-throttle-state\\use-throttle-state.spec.luau"]}]},{"name":"use-timeout","className":"ModuleScript","filePaths":["node_modules\\@rbxts\\pretty-react-hooks\\out\\use-timeout\\init.luau"],"children":[{"name":"use-timeout","className":"ModuleScript","filePaths":["node_modules\\@rbxts\\pretty-react-hooks\\out\\use-timeout\\use-timeout.luau"]},{"name":"use-timeout.spec","className":"ModuleScript","filePaths":["node_modules\\@rbxts\\pretty-react-hooks\\out\\use-timeout\\use-timeout.spec.luau"]}]},{"name":"use-timer","className":"ModuleScript","filePaths":["node_modules\\@rbxts\\pretty-react-hooks\\out\\use-timer\\init.luau"],"children":[{"name":"use-timer","className":"ModuleScript","filePaths":["node_modules\\@rbxts\\pretty-react-hooks\\out\\use-timer\\use-timer.luau"]},{"name":"use-timer.spec","className":"ModuleScript","filePaths":["node_modules\\@rbxts\\pretty-react-hooks\\out\\use-timer\\use-timer.spec.luau"]}]},{"name":"use-unmount-effect","className":"ModuleScript","filePaths":["node_modules\\@rbxts\\pretty-react-hooks\\out\\use-unmount-effect\\init.luau"],"children":[{"name":"use-unmount-effect","className":"ModuleScript","filePaths":["node_modules\\@rbxts\\pretty-react-hooks\\out\\use-unmount-effect\\use-unmount-effect.luau"]},{"name":"use-unmount-effect.spec","className":"ModuleScript","filePaths":["node_modules\\@rbxts\\pretty-react-hooks\\out\\use-unmount-effect\\use-unmount-effect.spec.luau"]}]},{"name":"use-update","className":"ModuleScript","filePaths":["node_modules\\@rbxts\\pretty-react-hooks\\out\\use-update\\init.luau"],"children":[{"name":"use-update","className":"ModuleScript","filePaths":["node_modules\\@rbxts\\pretty-react-hooks\\out\\use-update\\use-update.luau"]},{"name":"use-update.spec","className":"ModuleScript","filePaths":["node_modules\\@rbxts\\pretty-react-hooks\\out\\use-update\\use-update.spec.luau"]}]},{"name":"use-update-effect","className":"ModuleScript","filePaths":["node_modules\\@rbxts\\pretty-react-hooks\\out\\use-update-effect\\init.luau"],"children":[{"name":"use-update-effect","className":"ModuleScript","filePaths":["node_modules\\@rbxts\\pretty-react-hooks\\out\\use-update-effect\\use-update-effect.luau"]},{"name":"use-update-effect.spec","className":"ModuleScript","filePaths":["node_modules\\@rbxts\\pretty-react-hooks\\out\\use-update-effect\\use-update-effect.spec.luau"]}]},{"name":"use-viewport","className":"ModuleScript","filePaths":["node_modules\\@rbxts\\pretty-react-hooks\\out\\use-viewport\\init.luau"],"children":[{"name":"use-viewport","className":"ModuleScript","filePaths":["node_modules\\@rbxts\\pretty-react-hooks\\out\\use-viewport\\use-viewport.luau"]},{"name":"use-viewport.spec","className":"ModuleScript","filePaths":["node_modules\\@rbxts\\pretty-react-hooks\\out\\use-viewport\\use-viewport.spec.luau"]}]},{"name":"utils","className":"Folder","children":[{"name":"binding","className":"ModuleScript","filePaths":["node_modules\\@rbxts\\pretty-react-hooks\\out\\utils\\binding.luau"]},{"name":"hoarcekat","className":"ModuleScript","filePaths":["node_modules\\@rbxts\\pretty-react-hooks\\out\\utils\\hoarcekat.luau"]},{"name":"math","className":"ModuleScript","filePaths":["node_modules\\@rbxts\\pretty-react-hooks\\out\\utils\\math.luau"]},{"name":"shallow-equal","className":"ModuleScript","filePaths":["node_modules\\@rbxts\\pretty-react-hooks\\out\\utils\\shallow-equal.luau"]},{"name":"testez","className":"ModuleScript","filePaths":["node_modules\\@rbxts\\pretty-react-hooks\\out\\utils\\testez.luau"]}]}]}]},{"name":"react","className":"ModuleScript","filePaths":["node_modules\\@rbxts\\react\\src\\init.lua","node_modules\\@rbxts\\react\\default.project.json"],"children":[{"name":"tags","className":"ModuleScript","filePaths":["node_modules\\@rbxts\\react\\src\\tags.lua"]}]},{"name":"react-charm","className":"ModuleScript","filePaths":["node_modules\\@rbxts\\react-charm\\init.luau"],"children":[{"name":"src","className":"ModuleScript","filePaths":["node_modules\\@rbxts\\react-charm\\src\\init.luau"]},{"name":"wally","className":"ModuleScript","filePaths":["node_modules\\@rbxts\\react-charm\\wally.toml"]}]},{"name":"react-roblox","className":"ModuleScript","filePaths":["node_modules\\@rbxts\\react-roblox\\src\\init.lua","node_modules\\@rbxts\\react-roblox\\default.project.json"]},{"name":"repr","className":"Folder","children":[{"name":"out","className":"ModuleScript","filePaths":["node_modules\\@rbxts\\repr\\out\\init.luau"]}]},{"name":"ripple","className":"Folder","children":[{"name":"src","className":"ModuleScript","filePaths":["node_modules\\@rbxts\\ripple\\src\\init.luau"],"children":[{"name":"config","className":"ModuleScript","filePaths":["node_modules\\@rbxts\\ripple\\src\\config.luau"]},{"name":"createMotion","className":"ModuleScript","filePaths":["node_modules\\@rbxts\\ripple\\src\\createMotion.luau"]},{"name":"solvers","className":"Folder","children":[{"name":"immediate","className":"ModuleScript","filePaths":["node_modules\\@rbxts\\ripple\\src\\solvers\\immediate.luau"]},{"name":"linear","className":"ModuleScript","filePaths":["node_modules\\@rbxts\\ripple\\src\\solvers\\linear.luau"]},{"name":"spring","className":"ModuleScript","filePaths":["node_modules\\@rbxts\\ripple\\src\\solvers\\spring.luau"]},{"name":"tween","className":"ModuleScript","filePaths":["node_modules\\@rbxts\\ripple\\src\\solvers\\tween.luau"]}]},{"name":"types","className":"ModuleScript","filePaths":["node_modules\\@rbxts\\ripple\\src\\types.luau"]},{"name":"utils","className":"Folder","children":[{"name":"assign","className":"ModuleScript","filePaths":["node_modules\\@rbxts\\ripple\\src\\utils\\assign.luau"]},{"name":"intermediate","className":"ModuleScript","filePaths":["node_modules\\@rbxts\\ripple\\src\\utils\\intermediate.luau"]},{"name":"merge","className":"ModuleScript","filePaths":["node_modules\\@rbxts\\ripple\\src\\utils\\merge.luau"]},{"name":"snapshot","className":"ModuleScript","filePaths":["node_modules\\@rbxts\\ripple\\src\\utils\\snapshot.luau"]},{"name":"spy","className":"ModuleScript","filePaths":["node_modules\\@rbxts\\ripple\\src\\utils\\spy.luau"]}]}]}]},{"name":"serio","className":"Folder","children":[{"name":"out","className":"ModuleScript","filePaths":["node_modules\\@rbxts\\serio\\out\\init.luau"],"children":[{"name":"constants","className":"ModuleScript","filePaths":["node_modules\\@rbxts\\serio\\out\\constants.luau"]},{"name":"data-types","className":"ModuleScript","filePaths":["node_modules\\@rbxts\\serio\\out\\data-types.luau"]},{"name":"deserializer","className":"ModuleScript","filePaths":["node_modules\\@rbxts\\serio\\out\\deserializer.luau"]},{"name":"info-processing","className":"ModuleScript","filePaths":["node_modules\\@rbxts\\serio\\out\\info-processing.luau"]},{"name":"metadata","className":"ModuleScript","filePaths":["node_modules\\@rbxts\\serio\\out\\metadata\\init.luau"],"children":[{"name":"tuples","className":"ModuleScript","filePaths":["node_modules\\@rbxts\\serio\\out\\metadata\\tuples.luau"]},{"name":"unions","className":"ModuleScript","filePaths":["node_modules\\@rbxts\\serio\\out\\metadata\\unions.luau"]}]},{"name":"serializer","className":"ModuleScript","filePaths":["node_modules\\@rbxts\\serio\\out\\serializer.luau"]},{"name":"types","className":"ModuleScript","filePaths":["node_modules\\@rbxts\\serio\\out\\types.luau"]},{"name":"utility","className":"ModuleScript","filePaths":["node_modules\\@rbxts\\serio\\out\\utility\\init.luau"],"children":[{"name":"f16","className":"ModuleScript","filePaths":["node_modules\\@rbxts\\serio\\out\\utility\\f16.luau"]},{"name":"f24","className":"ModuleScript","filePaths":["node_modules\\@rbxts\\serio\\out\\utility\\f24.luau"]},{"name":"fastcalls","className":"ModuleScript","filePaths":["node_modules\\@rbxts\\serio\\out\\utility\\fastcalls.luau"]},{"name":"i24","className":"ModuleScript","filePaths":["node_modules\\@rbxts\\serio\\out\\utility\\i24.luau"]},{"name":"u24","className":"ModuleScript","filePaths":["node_modules\\@rbxts\\serio\\out\\utility\\u24.luau"]}]}]}]},{"name":"services","className":"ModuleScript","filePaths":["node_modules\\@rbxts\\services\\init.lua"]},{"name":"set-timeout","className":"Folder","children":[{"name":"out","className":"ModuleScript","filePaths":["node_modules\\@rbxts\\set-timeout\\out\\init.lua"],"children":[{"name":"debounce","className":"ModuleScript","filePaths":["node_modules\\@rbxts\\set-timeout\\out\\debounce.lua"]},{"name":"debounce.spec","className":"ModuleScript","filePaths":["node_modules\\@rbxts\\set-timeout\\out\\debounce.spec.lua"]},{"name":"set-countdown","className":"ModuleScript","filePaths":["node_modules\\@rbxts\\set-timeout\\out\\set-countdown.lua"]},{"name":"set-countdown.spec","className":"ModuleScript","filePaths":["node_modules\\@rbxts\\set-timeout\\out\\set-countdown.spec.lua"]},{"name":"set-interval","className":"ModuleScript","filePaths":["node_modules\\@rbxts\\set-timeout\\out\\set-interval.lua"]},{"name":"set-interval.spec","className":"ModuleScript","filePaths":["node_modules\\@rbxts\\set-timeout\\out\\set-interval.spec.lua"]},{"name":"set-timeout","className":"ModuleScript","filePaths":["node_modules\\@rbxts\\set-timeout\\out\\set-timeout.lua"]},{"name":"set-timeout.spec","className":"ModuleScript","filePaths":["node_modules\\@rbxts\\set-timeout\\out\\set-timeout.spec.lua"]},{"name":"throttle","className":"ModuleScript","filePaths":["node_modules\\@rbxts\\set-timeout\\out\\throttle.lua"]},{"name":"throttle.spec","className":"ModuleScript","filePaths":["node_modules\\@rbxts\\set-timeout\\out\\throttle.spec.lua"]}]}]},{"name":"signal","className":"ModuleScript","filePaths":["node_modules\\@rbxts\\signal\\init.lua"]},{"name":"t","className":"Folder","children":[{"name":"lib","className":"Folder","children":[{"name":"ts","className":"ModuleScript","filePaths":["node_modules\\@rbxts\\t\\lib\\ts.lua"]}]}]},{"name":"tether","className":"Folder","children":[{"name":"out","className":"ModuleScript","filePaths":["node_modules\\@rbxts\\tether\\out\\init.luau"],"children":[{"name":"builtin-middlewares","className":"ModuleScript","filePaths":["node_modules\\@rbxts\\tether\\out\\builtin-middlewares.luau"]},{"name":"emitters","className":"Folder","children":[{"name":"client-emitter","className":"ModuleScript","filePaths":["node_modules\\@rbxts\\tether\\out\\emitters\\client-emitter.luau"]},{"name":"contextual-emitter","className":"ModuleScript","filePaths":["node_modules\\@rbxts\\tether\\out\\emitters\\contextual-emitter.luau"]},{"name":"message-emitter","className":"ModuleScript","filePaths":["node_modules\\@rbxts\\tether\\out\\emitters\\message-emitter.luau"]},{"name":"server-emitter","className":"ModuleScript","filePaths":["node_modules\\@rbxts\\tether\\out\\emitters\\server-emitter.luau"]}]},{"name":"logging","className":"ModuleScript","filePaths":["node_modules\\@rbxts\\tether\\out\\logging.luau"]},{"name":"middleware","className":"ModuleScript","filePaths":["node_modules\\@rbxts\\tether\\out\\middleware.luau"]},{"name":"relayer","className":"ModuleScript","filePaths":["node_modules\\@rbxts\\tether\\out\\relayer.luau"]},{"name":"serdes","className":"ModuleScript","filePaths":["node_modules\\@rbxts\\tether\\out\\serdes.luau"]},{"name":"structs","className":"ModuleScript","filePaths":["node_modules\\@rbxts\\tether\\out\\structs.luau"]},{"name":"utility","className":"ModuleScript","filePaths":["node_modules\\@rbxts\\tether\\out\\utility.luau"]}]}]},{"name":"trash","className":"Folder","children":[{"name":"out","className":"ModuleScript","filePaths":["node_modules\\@rbxts\\trash\\out\\init.luau"]}]}]}]}]}]},{"name":"ServerScriptService","className":"ServerScriptService","children":[{"name":"TS","className":"Folder","children":[{"name":"handlers","className":"Folder","children":[{"name":"GunHandler","className":"Script","filePaths":["out\\server\\handlers\\GunHandler\\init.server.luau"],"children":[{"name":"GunClass","className":"ModuleScript","filePaths":["out\\server\\handlers\\GunHandler\\GunClass.luau"]}]},{"name":"OnPlayerJoin","className":"Script","filePaths":["out\\server\\handlers\\OnPlayerJoin.server.luau"]}]}]}]},{"name":"StarterPlayer","className":"StarterPlayer","children":[{"name":"StarterPlayerScripts","className":"StarterPlayerScripts","children":[{"name":"TS","className":"Folder","children":[{"name":"Events","className":"Folder","children":[{"name":"InputEvent","className":"LocalScript","filePaths":["out\\client\\Events\\InputEvent.client.luau"]}]}]}]}]}]}